[
  {
    "name": "PWAN Champion Realtors and Estates Limited",
    "heading": "Fraud Petitions against PWAN Champion Realtors and Estates Limited",
    "petitions": [
      {
        "file": "petitions/3.1_Million_Naira_Fake_Cheque_Petition_against_Pwan_Champion_Realtors_and_Estates_Limited.pdf",
        "title": "₦3,120,000.00 Investment Fraud petition against PWAN Champion Realtors and Estates Limited"
      },
      {
        "file": "petitions/55_Million_Naira_Land_Allocation_Fraud_Petition_against_Pwan_Champion_Realtors_and_Estates_Limited.pdf",
        "title": "₦55 million Land Allocation fraud against PWAN Champion Realtors and Estates Limited"
      },
      {
        "file": "petitions/2.4_Million_Petition_Against_PWAN_Asaba.pdf",
        "title": "₦2,400,000.00 Land Allocation petition against PWAN Champion Realtors and Estates Limited"
      },
      {
        "file": "petitions/agoifehintola@yahoo.com FEHINTOLA ABOSEDE AGOI.pdf",
        "title": "Petition 01: Investment Fraud Complaint"
      },
      {
        "file": "petitions/Arinze Chinedu.pdf",
        "title": "Petition 02: Alleged Land Scam"
      },
      {
        "file": "petitions/asouzunnamdi1@gmail.comAsouzu Samson chima.pdf",
        "title": "Petition 03: Double Allocation Report"
      },
      {
        "file": "petitions/Bamisile adebayo.pdf",
        "title": "Petition 04: Unreturned Investment Complaint"
      },
      {
        "file": "petitions/chiamakansionu@googlemail.comPhilippa Chiamaka Chinenye Nsionu.pdf",
        "title": "Petition 05: False Receipt Petition"
      },
      {
        "file": "petitions/chimeziekingsleychimezie084@gmail.comChimezie Ebubechi Kingsley.pdf",
        "title": "Petition 06: Property Fraud Allegation"
      },
      {
        "file": "petitions/ckingsley669@gmail.comChima Kingsley Ebuka.pdf",
        "title": "Petition 07: Payment Irregularities Claim"
      },
      {
        "file": "petitions/Divinewilliams337@gmail.comDivine Chima Williams.pdf",
        "title": "Petition 08: Delay in Plot Allocation"
      },
      {
        "file": "petitions/emekaedet@gmail Ekong Emeka Edet.pdf",
        "title": "Petition 09: Refund Dispute"
      },
      {
        "file": "petitions/emelifeokechukwu34@gmail.comEmelife Okechukwu John.pdf",
        "title": "Petition 10: Land Not Delivered"
      },
      {
        "file": "petitions/Esther Nwanko.pdf",
        "title": "Petition 11: Legal Action Threat Notice"
      },
      {
        "file": "petitions/Gabriel T Ezeorakwe.pdf",
        "title": "Petition 12: Allotment Fraud Complaint"
      },
      {
        "file": "petitions/gbemilekehart@gmail.comErnestential Hart Gbemileke.pdf",
        "title": "Petition 13: Non-Refund Dispute"
      },
      {
        "file": "petitions/godwinedojamichael@gmail.comGodwin Edoja Michael.pdf",
        "title": "Petition 14: Investment Loss Grievance"
      },
      {
        "file": "petitions/idera_ann@yahoo.comIdera Johnson.pdf",
        "title": "Petition 15: Repeated Delay in Allocation"
      },
      {
        "file": "petitions/ihimekpenroselyn@gmail.com Taiwo Christiana Ihimekpen.pdf",
        "title": "Petition 16: Breach of Promise Complaint"
      },
      {
        "file": "petitions/ihimekpenroselyn@gmail.comYetunde Roselyn Ihimekpen.pdf",
        "title": "Petition 17: Contractual Dispute Case"
      },
      {
        "file": "petitions/ikejiofor2008@yahoo.comChigozie Benneth Ikejiofor.pdf",
        "title": "Petition 18: Verification Failure Report"
      },
      {
        "file": "petitions/johnakushode@gmail.comJohn Akushode.pdf",
        "title": "Petition 19: Missing Land Allocation"
      },
      {
        "file": "petitions/kezfrank01@gmail.comUgochukwu Franklin Eze.pdf",
        "title": "Petition 20: Discrepancy in Allocation Letter"
      },
      {
        "file": "petitions/kinghenrikjr@gmail.comOKPOGADI CHIBUEZE HENRY.pdf",
        "title": "Petition 21: Fraudulent Transaction Alert"
      },
      {
        "file": "petitions/knightskillzz@gmail.com Chibueze Okey Umeanozie.pdf",
        "title": "Petition 22: Land Ownership Conflict"
      },
      {
        "file": "petitions/lizzy_adeleye@yahoo.comOluwatoyin Adeleye.pdf",
        "title": "Petition 23: Complaint of Misleading Contract"
      },
      {
        "file": "petitions/longepeter2@gmail.comLONGE PETER OPEMIPO.pdf",
        "title": "Petition 24: Land Scam Issue"
      },
      {
        "file": "petitions/melvin.alvin.33@gmail.comAbubakar Innocent.pdf",
        "title": "Petition 25: Plot Irregularities Report"
      },
      {
        "file": "petitions/molorunniwo@gmail.comOlalekan Seun Michael Olorunniwo.pdf",
        "title": "Petition 26: Deceptive Allocation Practices"
      },
      {
        "file": "petitions/Mr Afolabi Oseni.pdf",
        "title": "Petition 27: Legal Petition for Land Fraud"
      },
      {
        "file": "petitions/msteve698@gmail.comStephen Kabiyesi Martins.pdf",
        "title": "Petition 28: Breach of Agreement Notice"
      },
      {
        "file": "petitions/Muokee Chioma.pdf",
        "title": "Petition 29: Service Failure Complaint"
      }
    ]
  },
  {
    "name": "Sujimoto Construction Limited",
    "heading": "Petitions against Sujimoto Construction Limited",
    "petitions": [
      {
        "file": "petitions/10_MILLION_NAIRA_INVESTMENT_FRAUD_ALLEGATION_VS_SUJIMOTO_CONSTRUCTION_LIMITED.pdf",
        "title": "₦10 million Investment Fraud Allegation vs Sujimoto Construction Limited"
      },
      {
        "file": "petitions/70_MILLION_NAIRA_PETITION_AGAINST_SUJIMOTO_CONSTRUCTION_LIMITED_OVER_FRAUDULENT_MISAPPROPRIATION_OF_FUNDS_TOTALING.pdf",
        "title": "₦70 million Petition over Fraudulent Misappropriation of Funds"
      },
      {
        "file": "petitions/300_MILLION_NAIRA_INVESTMENT_FRAUD_ALLEGATION_VS_SUJIMOTO_CONSTRUCTION_LIMITED.pdf",
        "title": "₦300 million Investment Fraud Allegation vs Sujimoto Construction Limited"
      }
    ]
  }
]
